{
    "id": "04527A0E",
    "name": "Fusil à fléchettes en mousse X-Shot Dino Attack Claw Hunter (24 fléchettes, 6 oeufs)",
    "price": "2999",
    "image": "https://www.toysrus.ca/dw/image/v2/BDFX_PRD/on/demandware.static/-/Sites-toys-master-catalog/default/dw66cbe1aa/images/04527A0E_1.jpg",
    "description": "Fusil à fléchettes en mousse X-Shot Dino Attack Claw Hunter (24 fléchettes, 6 oeufs)",
    "url": "https://www.toysrus.ca/fr/Fusil-a-flechettes-en-mousse-X-Shot-Dino-Attack-Claw-Hunter--24%C2%A0flechettes--6%C2%A0oeufs-/04527A0E.html",
    "categories": [
        "1fjjZGjyQQ289DQZw1JMdw",
        "Up8qo1oqR2iddXr602l1jg",
        "MdvawtJvSomMvUa1KjQc_A",
        "-FDO8-8qSC6B2WuVoiR0Ew",
        "Ckm1jNfORo2_2e3G4NNbMw",
        "xspB9wMSSP-zceJbFhkAYA",
        "nR3vqPRmSISP5EWA8s8nXw",
        "YoWnZV46QhOKwjAMbt3Ibw"
    ]
}