{
    "id": "047F58E1",
    "name": "4\" Metal Figures - Transformers",
    "price": "1999",
    "image": "https://www.toysrus.ca/dw/image/v2/BDFX_PRD/on/demandware.static/-/Sites-toys-master-catalog/default/dw80dcadb7/images/047F58E1_1.jpg",
    "description": "4\" Metal Figures - Transformers",
    "url": "https://www.toysrus.ca/fr/4--Metal-Figures---Transformers/047F58E1.html",
    "categories": [
        "1fjjZGjyQQ289DQZw1JMdw",
        "hFPgaxjyTS-09FMgOvQS9g",
        "MdvawtJvSomMvUa1KjQc_A",
        "SoeT2PFORRuHrUwzGVMbug",
        "YoWnZV46QhOKwjAMbt3Ibw"
    ]
}