{
    "id": "04951A8B",
    "name": "Nebulous Stars - Peinture Par Autocollants",
    "price": "2499",
    "image": "https://www.toysrus.ca/dw/image/v2/BDFX_PRD/on/demandware.static/-/Sites-toys-master-catalog/default/dwf32e9727/images/04951A8B_1.jpg",
    "description": "Nebulous Stars - Peinture Par Autocollants",
    "url": "https://www.toysrus.ca/fr/Nebulous-Stars---Peinture-Par-Autocollants/04951A8B.html",
    "categories": [
        "1fjjZGjyQQ289DQZw1JMdw",
        "oum-7vxuTbeC_7cuZaEQBA",
        "MdvawtJvSomMvUa1KjQc_A",
        "48KozXkQQwW-SwABoirVRw",
        "YoWnZV46QhOKwjAMbt3Ibw"
    ]
}