{
    "id": "0EE6F83C",
    "name": "Méga coffret Mon Lecteur Leap, lecteur et livres - Version anglaise",
    "price": 6999,
    "image": "https://www.toysrus.ca/dw/image/v2/BDFX_PRD/on/demandware.static/-/Sites-toys-master-catalog/default/dwa30b4fe8/images/0EE6F83C_1.jpg",
    "description": "Méga coffret Mon Lecteur Leap, lecteur et livres - Version anglaise",
    "url": "https://www.toysrus.ca/fr/Mega-coffret-Mon-Lecteur-Leap--lecteur-et-livres---Version-anglaise/0EE6F83C.html",
    "categories": [
        "KZZsR5bdRIC5lTNJeyihTw",
        "MdvawtJvSomMvUa1KjQc_A",
        "yxmm504pSfqjUZkwHqug1Q",
        "H-0oXd77RpuqhVvQ4Ncdlw",
        "Xgn7P7_hTGGElQZn0i_c5A",
        "SqNRVU9HTHuhIqHxOJaN8w",
        "YoWnZV46QhOKwjAMbt3Ibw"
    ]
}