{
    "id": "14A73A22",
    "name": "Barbie -It Takes Two -Vive le camping, poupée Daisy, animal",
    "price": 3999,
    "image": "https://www.toysrus.ca/dw/image/v2/BDFX_PRD/on/demandware.static/-/Sites-toys-master-catalog/default/dwc96d29cc/images/14A73A22_1.jpg",
    "description": "Barbie -It Takes Two -Vive le camping, poupée Daisy, animal",
    "url": "https://www.toysrus.ca/fr/Barbie--It-Takes-Two--Vive-le-camping--poupee-Daisy--animal/14A73A22.html",
    "categories": [
        "vdjSQqKnTw6VVik-7a3i3g",
        "MdvawtJvSomMvUa1KjQc_A",
        "kSzVH6Q3RdGcG-yk9-k2jg",
        "omLQner7Ssm_qB_TXJDkGA",
        "-CF92pItTH2OCr5NML3LLw",
        "YoWnZV46QhOKwjAMbt3Ibw"
    ]
}