{
    "id": "14D199BD",
    "name": "Jeu de cartes Diary Of A Wimpy Kid - Flippin' Frenzy - Édition anglaise",
    "price": 999,
    "image": "https://www.toysrus.ca/dw/image/v2/BDFX_PRD/on/demandware.static/-/Sites-toys-master-catalog/default/dw7c18a271/images/14D199BD_1.jpg",
    "description": "Jeu de cartes Diary Of A Wimpy Kid - Flippin' Frenzy - Édition anglaise",
    "url": "https://www.toysrus.ca/fr/Jeu-de-cartes-Diary-Of-A-Wimpy-Kid---Flippin--Frenzy---Edition-anglaise/14D199BD.html",
    "categories": [
        "1fjjZGjyQQ289DQZw1JMdw",
        "KZZsR5bdRIC5lTNJeyihTw",
        "MdvawtJvSomMvUa1KjQc_A",
        "H_wmbx3lSDmpJYqSeU4WRA",
        "V8SwQvVESCO7wX8XxLoZEA",
        "YoWnZV46QhOKwjAMbt3Ibw"
    ]
}