{
    "id": "241C480E",
    "name": "Treasure X Lost Lands Skull Island Skull Temple Mega Playset",
    "price": 6999,
    "image": "https://www.toysrus.ca/dw/image/v2/BDFX_PRD/on/demandware.static/-/Sites-toys-master-catalog/default/dw91cecb24/images/241C480E_1.jpg",
    "description": "Treasure X Lost Lands Skull Island Skull Temple Mega Playset",
    "url": "https://www.toysrus.ca/fr/Treasure-X-Lost-Lands-Skull-Island-Skull-Temple-Mega-Playset/241C480E.html",
    "categories": [
        "hFPgaxjyTS-09FMgOvQS9g",
        "KZZsR5bdRIC5lTNJeyihTw",
        "MdvawtJvSomMvUa1KjQc_A",
        "SoeT2PFORRuHrUwzGVMbug",
        "YoWnZV46QhOKwjAMbt3Ibw"
    ]
}