{
    "id": "247F69C4",
    "name": "Mega Barbie Kiosque de crème glacée et décapotable rose à construire",
    "price": 2499,
    "image": "https://www.toysrus.ca/dw/image/v2/BDFX_PRD/on/demandware.static/-/Sites-toys-master-catalog/default/dw095a5441/images/247F69C4_1.jpg",
    "description": "Mega Barbie Kiosque de crème glacée et décapotable rose à construire",
    "url": "https://www.toysrus.ca/fr/Mega-Barbie-Kiosque-de-creme-glacee-et-decapotable-rose-a-construire/247F69C4.html",
    "categories": [
        "1fjjZGjyQQ289DQZw1JMdw",
        "KZZsR5bdRIC5lTNJeyihTw",
        "MdvawtJvSomMvUa1KjQc_A",
        "yMgFZPBSSbS0W0_67S6H2A",
        "YoWnZV46QhOKwjAMbt3Ibw"
    ]
}