{
    "id": "248F98F5",
    "name": "Disney - Minnie Mouse en peluche Noël",
    "price": 2499,
    "image": "https://www.toysrus.ca/dw/image/v2/BDFX_PRD/on/demandware.static/-/Sites-toys-master-catalog/default/dwec12b40b/images/248F98F5_1.jpg",
    "description": "Disney - Minnie Mouse en peluche Noël",
    "url": "https://www.toysrus.ca/fr/Disney---Minnie-Mouse-en-peluche-Noel/248F98F5.html",
    "categories": [
        "rFlTVotoSuuUXYkfGrXA2A",
        "vdjSQqKnTw6VVik-7a3i3g",
        "MdvawtJvSomMvUa1KjQc_A",
        "YoWnZV46QhOKwjAMbt3Ibw"
    ]
}