{
    "id": "2490797E",
    "name": "PLAYGO-Camion à benne toujours prêt",
    "price": 1699,
    "image": "https://www.toysrus.ca/dw/image/v2/BDFX_PRD/on/demandware.static/-/Sites-toys-master-catalog/default/dwabdf963f/images/2490797E_1.jpg",
    "description": "PLAYGO-Camion à benne toujours prêt",
    "url": "https://www.toysrus.ca/fr/PLAYGO-Camion-a-benne-toujours-pret/2490797E.html",
    "categories": [
        "vdjSQqKnTw6VVik-7a3i3g",
        "k1dYuCMyRxenOpsOzZXidg",
        "MdvawtJvSomMvUa1KjQc_A",
        "U-n9wowiS5W0FO43ivGuig",
        "JptOk_sgRPO6qa9Ojjq5pA",
        "nLE2pK09RWWGiTrGV-IhRw",
        "YoWnZV46QhOKwjAMbt3Ibw"
    ]
}