{
    "id": "3428EA58",
    "name": "Poupée Barbie- Poupée Ballerine blonde - Lumières magiques",
    "price": "3499",
    "image": "https://www.toysrus.ca/dw/image/v2/BDFX_PRD/on/demandware.static/-/Sites-toys-master-catalog/default/dw625ad453/images/3428EA58_1.jpg",
    "description": "Poupée Barbie- Poupée Ballerine blonde - Lumières magiques",
    "url": "https://www.toysrus.ca/fr/Poupee-Barbie--Poupee-Ballerine-blonde---Lumieres-magiques/3428EA58.html",
    "categories": [
        "vdjSQqKnTw6VVik-7a3i3g",
        "KZZsR5bdRIC5lTNJeyihTw",
        "MdvawtJvSomMvUa1KjQc_A",
        "kSzVH6Q3RdGcG-yk9-k2jg",
        "omLQner7Ssm_qB_TXJDkGA",
        "-CF92pItTH2OCr5NML3LLw",
        "YoWnZV46QhOKwjAMbt3Ibw"
    ]
}