{
    "id": "41D70F68",
    "name": "Pavilion - De luxe Mancala",
    "price": 2499,
    "image": "https://www.toysrus.ca/dw/image/v2/BDFX_PRD/on/demandware.static/-/Sites-toys-master-catalog/default/dwff993b7e/images/41D70F68_1.jpg",
    "description": "Pavilion - De luxe Mancala",
    "url": "https://www.toysrus.ca/fr/Pavilion---De-luxe-Mancala/41D70F68.html",
    "categories": [
        "Up8qo1oqR2iddXr602l1jg",
        "MdvawtJvSomMvUa1KjQc_A",
        "xQB8DNTQRQ-dnL7UmEQNiw",
        "H_wmbx3lSDmpJYqSeU4WRA",
        "YoWnZV46QhOKwjAMbt3Ibw"
    ]
}