{
    "id": "440C69F8",
    "name": "VTech Baby baladeur des découvertes - Édition française",
    "price": "1499",
    "image": "https://www.toysrus.ca/dw/image/v2/BDFX_PRD/on/demandware.static/-/Sites-toys-master-catalog/default/dw45632e47/images/440C69F8_1.jpg",
    "description": "VTech Baby baladeur des découvertes - Édition française",
    "url": "https://www.toysrus.ca/fr/VTech-Baby-baladeur-des-decouvertes---Edition-francaise/440C69F8.html",
    "categories": [
        "MdvawtJvSomMvUa1KjQc_A",
        "ufviqKmGQNq5gej63royHg",
        "nLE2pK09RWWGiTrGV-IhRw",
        "YoWnZV46QhOKwjAMbt3Ibw"
    ]
}