{
    "id": "440F39BD",
    "name": "Jeu Pokémon Attaque surprise",
    "price": "3299",
    "image": "https://www.toysrus.ca/dw/image/v2/BDFX_PRD/on/demandware.static/-/Sites-toys-master-catalog/default/dw9786c79b/images/440F39BD_1.jpg",
    "description": "Jeu Pokémon Attaque surprise",
    "url": "https://www.toysrus.ca/fr/Jeu-Pokemon-Attaque-surprise/440F39BD.html",
    "categories": [
        "2LAIi61IROKwIcGCtn1n1g",
        "LRsfCDC0TyG2dyvcxjN-ig",
        "KZZsR5bdRIC5lTNJeyihTw",
        "MdvawtJvSomMvUa1KjQc_A",
        "YoWnZV46QhOKwjAMbt3Ibw"
    ]
}