{
    "id": "4422387B",
    "name": "Nerf Hyper, cartouche de 50 billes en mousse",
    "price": "1999",
    "image": "https://www.toysrus.ca/dw/image/v2/BDFX_PRD/on/demandware.static/-/Sites-toys-master-catalog/default/dw41298d12/images/4422387B_1.jpg",
    "description": "Nerf Hyper, cartouche de 50 billes en mousse",
    "url": "https://www.toysrus.ca/fr/Nerf-Hyper--cartouche-de-50-billes-en-mousse/4422387B.html",
    "categories": [
        "KP8kb676TQ6gg32Hm8mimg",
        "MdvawtJvSomMvUa1KjQc_A",
        "-FDO8-8qSC6B2WuVoiR0Ew",
        "Ckm1jNfORo2_2e3G4NNbMw",
        "xspB9wMSSP-zceJbFhkAYA",
        "nR3vqPRmSISP5EWA8s8nXw",
        "YoWnZV46QhOKwjAMbt3Ibw"
    ]
}