{
    "id": "448FB840",
    "name": "Magic Mixies Eau De Chaudron Surprise Gem Magique",
    "price": 3999,
    "image": "https://www.toysrus.ca/dw/image/v2/BDFX_PRD/on/demandware.static/-/Sites-toys-master-catalog/default/dwd05b6df2/images/448FB840_1.jpg",
    "description": "Magic Mixies Eau De Chaudron Surprise Gem Magique",
    "url": "https://www.toysrus.ca/fr/Magic-Mixies-Eau-De-Chaudron-Surprise-Gem-Magique/448FB840.html",
    "categories": [
        "KZZsR5bdRIC5lTNJeyihTw",
        "MdvawtJvSomMvUa1KjQc_A",
        "E7HvAgCgQmiDIthWj-waHQ",
        "kSzVH6Q3RdGcG-yk9-k2jg",
        "YoWnZV46QhOKwjAMbt3Ibw"
    ]
}