{
    "id": "54153991",
    "name": "Pokémon Dresseur Guess Sinnoh - Édition anglaise",
    "price": "2999",
    "image": "https://www.toysrus.ca/dw/image/v2/BDFX_PRD/on/demandware.static/-/Sites-toys-master-catalog/default/dwa2200bd7/images/54153991_1.jpg",
    "description": "Pokémon Dresseur Guess Sinnoh - Édition anglaise",
    "url": "https://www.toysrus.ca/fr/Pokemon-Dresseur-Guess-Sinnoh---Edition-anglaise/54153991.html",
    "categories": [
        "KZZsR5bdRIC5lTNJeyihTw",
        "MdvawtJvSomMvUa1KjQc_A",
        "H_wmbx3lSDmpJYqSeU4WRA",
        "V8SwQvVESCO7wX8XxLoZEA",
        "YoWnZV46QhOKwjAMbt3Ibw"
    ]
}