{
    "id": "5423494E",
    "name": "Poupée-mannequin LOL Surprise OMG Fierce, Neonlicious",
    "price": "5999",
    "image": "https://www.toysrus.ca/dw/image/v2/BDFX_PRD/on/demandware.static/-/Sites-toys-master-catalog/default/dw49df4343/images/5423494E_1.jpg",
    "description": "Poupée-mannequin LOL Surprise OMG Fierce, Neonlicious",
    "url": "https://www.toysrus.ca/fr/Poupee-mannequin-LOL-Surprise-OMG-Fierce--Neonlicious/5423494E.html",
    "categories": [
        "KZZsR5bdRIC5lTNJeyihTw",
        "MdvawtJvSomMvUa1KjQc_A",
        "E7HvAgCgQmiDIthWj-waHQ",
        "kSzVH6Q3RdGcG-yk9-k2jg",
        "omLQner7Ssm_qB_TXJDkGA",
        "-CF92pItTH2OCr5NML3LLw",
        "YoWnZV46QhOKwjAMbt3Ibw"
    ]
}