{
    "id": "54435A80",
    "name": "Assortiment de camions Monster Bigfoot, échelle 1:24 (Choisir Flamme bleue ou Morsure de serpent)",
    "price": 3999,
    "image": "https://www.toysrus.ca/dw/image/v2/BDFX_PRD/on/demandware.static/-/Sites-toys-master-catalog/default/dw685b569f/images/54435A80_1.jpg",
    "description": "Assortiment de camions Monster Bigfoot, échelle 1:24 (Choisir Flamme bleue ou Morsure de serpent)",
    "url": "https://www.toysrus.ca/fr/Assortiment-de-camions-Monster-Bigfoot--echelle-1-24--Choisir-Flamme-bleue-ou-Morsure-de-serpent-/54435A80.html",
    "categories": [
        "wYgFNB95QCmf5mGFPepKEQ",
        "1fjjZGjyQQ289DQZw1JMdw",
        "wlyJQQk8SBejboMAer5DRg",
        "KZZsR5bdRIC5lTNJeyihTw",
        "MdvawtJvSomMvUa1KjQc_A",
        "JptOk_sgRPO6qa9Ojjq5pA",
        "YoWnZV46QhOKwjAMbt3Ibw"
    ]
}