{
    "id": "544C7B9E",
    "name": "LEGO Ideas Winnie l'ourson 21326 (1265 pièces)",
    "price": "14499",
    "image": "https://www.toysrus.ca/dw/image/v2/BDFX_PRD/on/demandware.static/-/Sites-toys-master-catalog/default/dwb5803b13/images/544C7B9E_1.jpg",
    "description": "LEGO Ideas Winnie l'ourson 21326 (1265 pièces)",
    "url": "https://www.toysrus.ca/fr/LEGO-Ideas-Winnie-l-ourson-21326--1265-pieces-/544C7B9E.html",
    "categories": [
        "KP8kb676TQ6gg32Hm8mimg",
        "MdvawtJvSomMvUa1KjQc_A",
        "yMgFZPBSSbS0W0_67S6H2A",
        "YoWnZV46QhOKwjAMbt3Ibw"
    ]
}