{
    "id": "54A03B89",
    "name": "It (1990) Pennywise V.2 - Édition Anglaise",
    "price": 5999,
    "image": "https://www.toysrus.ca/dw/image/v2/BDFX_PRD/on/demandware.static/-/Sites-toys-master-catalog/default/dw7780efdd/images/54A03B89_1.jpg",
    "description": "It (1990) Pennywise V.2 - Édition Anglaise",
    "url": "https://www.toysrus.ca/fr/It--1990--Pennywise-V.2---Edition-Anglaise/54A03B89.html",
    "categories": [
        "2LAIi61IROKwIcGCtn1n1g",
        "1fjjZGjyQQ289DQZw1JMdw",
        "LRsfCDC0TyG2dyvcxjN-ig",
        "hFPgaxjyTS-09FMgOvQS9g",
        "MdvawtJvSomMvUa1KjQc_A",
        "SoeT2PFORRuHrUwzGVMbug",
        "YoWnZV46QhOKwjAMbt3Ibw"
    ]
}