{
    "id": "640EABFD",
    "name": "Speed Duel GX Yu-Gi-Oh! : Duellistes des Ombres - Édition anglaise",
    "price": "4499",
    "image": "https://www.toysrus.ca/dw/image/v2/BDFX_PRD/on/demandware.static/-/Sites-toys-master-catalog/default/dw630c5636/images/640EABFD_1.jpg",
    "description": "Speed Duel GX Yu-Gi-Oh! : Duellistes des Ombres - Édition anglaise",
    "url": "https://www.toysrus.ca/fr/Speed-Duel-GX-Yu-Gi-Oh--Duellistes-des-Ombres---Edition-anglaise/640EABFD.html",
    "categories": [
        "1fjjZGjyQQ289DQZw1JMdw",
        "KZZsR5bdRIC5lTNJeyihTw",
        "MdvawtJvSomMvUa1KjQc_A",
        "SoeT2PFORRuHrUwzGVMbug",
        "-t7XaQqaQTSXtyLMVTu4NQ",
        "YoWnZV46QhOKwjAMbt3Ibw"
    ]
}