{
    "id": "645BCA42",
    "name": "Jeté Squishmallows \"On Cloud Nine\"",
    "price": 2699,
    "image": "https://www.toysrus.ca/dw/image/v2/BDFX_PRD/on/demandware.static/-/Sites-toys-master-catalog/default/dw5ad071c5/images/645BCA42_1.jpg",
    "description": "Jeté Squishmallows \"On Cloud Nine\"",
    "url": "https://www.toysrus.ca/fr/Jete-Squishmallows--On-Cloud-Nine-/645BCA42.html",
    "categories": [
        "vdjSQqKnTw6VVik-7a3i3g",
        "SSD5eBk3Tba-zfF37IIhvQ",
        "MdvawtJvSomMvUa1KjQc_A",
        "7LQShfVYQgmtUADWdj0_kg",
        "YoWnZV46QhOKwjAMbt3Ibw"
    ]
}