{
    "id": "647C28A1",
    "name": "LeapFrog Carte du monde interactive - Édition française",
    "price": "5499",
    "image": "https://www.toysrus.ca/dw/image/v2/BDFX_PRD/on/demandware.static/-/Sites-toys-master-catalog/default/dw19e4f085/images/647C28A1_1.jpg",
    "description": "LeapFrog Carte du monde interactive - Édition française",
    "url": "https://www.toysrus.ca/fr/LeapFrog-Carte-du-monde-interactive---Edition-francaise/647C28A1.html",
    "categories": [
        "vdjSQqKnTw6VVik-7a3i3g",
        "MdvawtJvSomMvUa1KjQc_A",
        "yxmm504pSfqjUZkwHqug1Q",
        "H-0oXd77RpuqhVvQ4Ncdlw",
        "Xgn7P7_hTGGElQZn0i_c5A",
        "SqNRVU9HTHuhIqHxOJaN8w",
        "YoWnZV46QhOKwjAMbt3Ibw"
    ]
}