{
    "id": "648CEBAC",
    "name": "Polly Pocket - Connexions animales - Coffret empilable, poupée, animal",
    "price": "1099",
    "image": "https://www.toysrus.ca/dw/image/v2/BDFX_PRD/on/demandware.static/-/Sites-toys-master-catalog/default/dwc1aedd41/images/648CEBAC_1.jpg",
    "description": "Polly Pocket - Connexions animales - Coffret empilable, poupée, animal",
    "url": "https://www.toysrus.ca/fr/Polly-Pocket---Connexions-animales---Coffret-empilable--poupee--animal/648CEBAC.html",
    "categories": [
        "vdjSQqKnTw6VVik-7a3i3g",
        "KZZsR5bdRIC5lTNJeyihTw",
        "MdvawtJvSomMvUa1KjQc_A",
        "E7HvAgCgQmiDIthWj-waHQ",
        "kSzVH6Q3RdGcG-yk9-k2jg",
        "YoWnZV46QhOKwjAMbt3Ibw"
    ]
}