{
    "id": "64B3DBA1",
    "name": "Hot Wheels Skate Coffret de jeu Planchodrome Beignerie",
    "price": "2299",
    "image": "https://www.toysrus.ca/dw/image/v2/BDFX_PRD/on/demandware.static/-/Sites-toys-master-catalog/default/dwa1e4fbb9/images/64B3DBA1_1.jpg",
    "description": "Hot Wheels Skate Coffret de jeu Planchodrome Beignerie",
    "url": "https://www.toysrus.ca/fr/Hot-Wheels-Skate-Coffret-de-jeu-Planchodrome-Beignerie/64B3DBA1.html",
    "categories": [
        "KZZsR5bdRIC5lTNJeyihTw",
        "MdvawtJvSomMvUa1KjQc_A",
        "JptOk_sgRPO6qa9Ojjq5pA",
        "V6F5qJDST4-SDE3PvCAjqg",
        "YoWnZV46QhOKwjAMbt3Ibw"
    ]
}