{
    "id": "64E1291F",
    "name": "J'Adore Set De Glace De Luxe",
    "price": "3499",
    "image": "https://www.toysrus.ca/dw/image/v2/BDFX_PRD/on/demandware.static/-/Sites-toys-master-catalog/default/dw0b9b0611/images/64E1291F_1.jpg",
    "description": "J'Adore Set De Glace De Luxe",
    "url": "https://www.toysrus.ca/fr/J-Adore-Set-De-Glace-De-Luxe/64E1291F.html",
    "categories": [
        "vdjSQqKnTw6VVik-7a3i3g",
        "MdvawtJvSomMvUa1KjQc_A",
        "Ek5AfUwASGWAcmFz9SzzoQ",
        "YoWnZV46QhOKwjAMbt3Ibw"
    ]
}