{
    "id": "64EFB8AC",
    "name": "Peppa Pig - Vélo 12 po - Notre exclusivité",
    "price": "15499",
    "image": "https://www.toysrus.ca/dw/image/v2/BDFX_PRD/on/demandware.static/-/Sites-toys-master-catalog/default/dwedecfbbc/images/64EFB8AC_1.jpg",
    "description": "Peppa Pig - Vélo 12 po - Notre exclusivité",
    "url": "https://www.toysrus.ca/fr/Peppa-Pig---Velo-12-po---Notre-exclusivite/64EFB8AC.html",
    "categories": [
        "vdjSQqKnTw6VVik-7a3i3g",
        "MdvawtJvSomMvUa1KjQc_A",
        "NE2J3XeCSvaEpkO46botmw",
        "hVSzt2gbTWutwbGYjM_4ww",
        "SHjaThM-SLy196TSdjHm6w",
        "nR3vqPRmSISP5EWA8s8nXw",
        "YoWnZV46QhOKwjAMbt3Ibw"
    ]
}