{
    "id": "7457F8EF",
    "name": "MONOPOLY: Queen - Édition anglaise",
    "price": "5999",
    "image": "https://www.toysrus.ca/dw/image/v2/BDFX_PRD/on/demandware.static/-/Sites-toys-master-catalog/default/dwec8ef2b6/images/7457F8EF_1.jpg",
    "description": "MONOPOLY: Queen - Édition anglaise",
    "url": "https://www.toysrus.ca/fr/MONOPOLY--Queen---Edition-anglaise/7457F8EF.html",
    "categories": [
        "1fjjZGjyQQ289DQZw1JMdw",
        "MdvawtJvSomMvUa1KjQc_A",
        "H_wmbx3lSDmpJYqSeU4WRA",
        "YoWnZV46QhOKwjAMbt3Ibw"
    ]
}