{
    "id": "74A07838",
    "name": "LeapFrog PAW Patrol: Pat Patrouille - Mon livre-jeu Mission Alphabet - Édition française",
    "price": 3499,
    "image": "https://www.toysrus.ca/dw/image/v2/BDFX_PRD/on/demandware.static/-/Sites-toys-master-catalog/default/dwf1f8540b/images/74A07838_1.jpg",
    "description": "LeapFrog PAW Patrol: Pat Patrouille - Mon livre-jeu Mission Alphabet - Édition française",
    "url": "https://www.toysrus.ca/fr/LeapFrog-PAW-Patrol--Pat-Patrouille---Mon-livre-jeu-Mission-Alphabet---Edition-francaise/74A07838.html",
    "categories": [
        "vdjSQqKnTw6VVik-7a3i3g",
        "MdvawtJvSomMvUa1KjQc_A",
        "yxmm504pSfqjUZkwHqug1Q",
        "SqNRVU9HTHuhIqHxOJaN8w",
        "YoWnZV46QhOKwjAMbt3Ibw"
    ]
}