{
    "id": "74C059FE",
    "name": "Jurassic World - Peluche - Tyrannosaure rex, morsure et sons",
    "price": 4999,
    "image": "https://www.toysrus.ca/dw/image/v2/BDFX_PRD/on/demandware.static/-/Sites-toys-master-catalog/default/dwe5e63096/images/74C059FE_1.jpg",
    "description": "Jurassic World - Peluche - Tyrannosaure rex, morsure et sons",
    "url": "https://www.toysrus.ca/fr/Jurassic-World---Peluche---Tyrannosaure-rex--morsure-et-sons/74C059FE.html",
    "categories": [
        "2LAIi61IROKwIcGCtn1n1g",
        "LRsfCDC0TyG2dyvcxjN-ig",
        "vdjSQqKnTw6VVik-7a3i3g",
        "KZZsR5bdRIC5lTNJeyihTw",
        "MdvawtJvSomMvUa1KjQc_A",
        "YoWnZV46QhOKwjAMbt3Ibw"
    ]
}