{
    "id": "848EEA4B",
    "name": "Marvel Studios' Black Panther : Wakanda Forever, jouet de déguisement Lance électronique Kingsguard",
    "price": "2118",
    "image": "https://www.toysrus.ca/dw/image/v2/BDFX_PRD/on/demandware.static/-/Sites-toys-master-catalog/default/dwb33ef552/images/848EEA4B_2.jpg",
    "description": "Marvel Studios' Black Panther : Wakanda Forever, jouet de déguisement Lance électronique Kingsguard",
    "url": "https://www.toysrus.ca/fr/Marvel-Studios--Black-Panther%C2%A0--Wakanda-Forever--jouet-de-deguisement-Lance-electronique-Kingsguard/848EEA4B.html",
    "categories": [
        "2LAIi61IROKwIcGCtn1n1g",
        "psgy3esBSJubwV3AY-AYnw",
        "LRsfCDC0TyG2dyvcxjN-ig",
        "KZZsR5bdRIC5lTNJeyihTw",
        "MdvawtJvSomMvUa1KjQc_A",
        "Ek5AfUwASGWAcmFz9SzzoQ",
        "YoWnZV46QhOKwjAMbt3Ibw"
    ]
}