{
    "id": "94725A12",
    "name": "Mini oeuf de dinosaure jurassique allumant Smashers par ZURU",
    "price": 1699,
    "image": "https://www.toysrus.ca/dw/image/v2/BDFX_PRD/on/demandware.static/-/Sites-toys-master-catalog/default/dw2c4e440f/images/94725A12_1.jpg",
    "description": "Mini oeuf de dinosaure jurassique allumant Smashers par ZURU",
    "url": "https://www.toysrus.ca/fr/Mini-oeuf-de-dinosaure-jurassique-allumant-Smashers-par-ZURU/94725A12.html",
    "categories": [
        "hFPgaxjyTS-09FMgOvQS9g",
        "vdjSQqKnTw6VVik-7a3i3g",
        "KZZsR5bdRIC5lTNJeyihTw",
        "MdvawtJvSomMvUa1KjQc_A",
        "SoeT2PFORRuHrUwzGVMbug",
        "YoWnZV46QhOKwjAMbt3Ibw"
    ]
}