{
    "id": "94E9E89F",
    "name": "Ideal Games - Shuffler de carte électronique",
    "price": "1699",
    "image": "https://www.toysrus.ca/dw/image/v2/BDFX_PRD/on/demandware.static/-/Sites-toys-master-catalog/default/dw570392ee/images/94E9E89F_1.jpg",
    "description": "Ideal Games - Shuffler de carte électronique",
    "url": "https://www.toysrus.ca/fr/Ideal-Games---Shuffler-de-carte-electronique/94E9E89F.html",
    "categories": [
        "1fjjZGjyQQ289DQZw1JMdw",
        "MdvawtJvSomMvUa1KjQc_A",
        "H_wmbx3lSDmpJYqSeU4WRA",
        "V8SwQvVESCO7wX8XxLoZEA",
        "YoWnZV46QhOKwjAMbt3Ibw"
    ]
}