{
    "id": "A3C2BA73",
    "name": "Pinceaux plats - 4 ct",
    "price": 599,
    "image": "https://www.toysrus.ca/dw/image/v2/BDFX_PRD/on/demandware.static/-/Sites-toys-master-catalog/default/dw3569a606/images/A3C2BA73_1.jpg",
    "description": "Pinceaux plats - 4 ct",
    "url": "https://www.toysrus.ca/fr/Pinceaux-plats---4-ct/A3C2BA73.html",
    "categories": [
        "oum-7vxuTbeC_7cuZaEQBA",
        "vdjSQqKnTw6VVik-7a3i3g",
        "MdvawtJvSomMvUa1KjQc_A",
        "UohZnJvtQ0KaBYNj-NIQ4g",
        "YoWnZV46QhOKwjAMbt3Ibw"
    ]
}