{
    "id": "A45B583E",
    "name": "Deck de Combat Pokémon Origin Forme Palkia VSTAR - Édition anglaise",
    "price": "4999",
    "image": "https://www.toysrus.ca/dw/image/v2/BDFX_PRD/on/demandware.static/-/Sites-toys-master-catalog/default/dw7339f046/images/A45B583E_1.jpg",
    "description": "Deck de Combat Pokémon Origin Forme Palkia VSTAR - Édition anglaise",
    "url": "https://www.toysrus.ca/fr/Deck-de-Combat-Pokemon-Origin-Forme-Palkia-VSTAR---Edition-anglaise/A45B583E.html",
    "categories": [
        "1fjjZGjyQQ289DQZw1JMdw",
        "KZZsR5bdRIC5lTNJeyihTw",
        "MdvawtJvSomMvUa1KjQc_A",
        "SoeT2PFORRuHrUwzGVMbug",
        "-t7XaQqaQTSXtyLMVTu4NQ",
        "YoWnZV46QhOKwjAMbt3Ibw"
    ]
}