{
    "id": "A4637B93",
    "name": "CoComelon JJ qui danse - Édition anglaise",
    "price": 4999,
    "image": "https://www.toysrus.ca/dw/image/v2/BDFX_PRD/on/demandware.static/-/Sites-toys-master-catalog/default/dwd76ed65e/images/A4637B93_1.jpg",
    "description": "CoComelon JJ qui danse - Édition anglaise",
    "url": "https://www.toysrus.ca/fr/CoComelon-JJ-qui-danse---Edition-anglaise/A4637B93.html",
    "categories": [
        "k1dYuCMyRxenOpsOzZXidg",
        "MdvawtJvSomMvUa1KjQc_A",
        "ufviqKmGQNq5gej63royHg",
        "nLE2pK09RWWGiTrGV-IhRw",
        "YoWnZV46QhOKwjAMbt3Ibw"
    ]
}