{
    "id": "A4BB5842",
    "name": "​MEGA - Pokémon - Pikachu en mouvement",
    "price": "12499",
    "image": "https://www.toysrus.ca/dw/image/v2/BDFX_PRD/on/demandware.static/-/Sites-toys-master-catalog/default/dwb73d6c21/images/A4BB5842_1.jpg",
    "description": "​MEGA - Pokémon - Pikachu en mouvement",
    "url": "https://www.toysrus.ca/fr/%E2%80%8BMEGA---Pokemon---Pikachu-en-mouvement/A4BB5842.html",
    "categories": [
        "Up8qo1oqR2iddXr602l1jg",
        "MdvawtJvSomMvUa1KjQc_A",
        "yMgFZPBSSbS0W0_67S6H2A",
        "YoWnZV46QhOKwjAMbt3Ibw"
    ]
}