{
    "id": "B43B6AED",
    "name": "Little Lot - Rampe de voiture Swirly Whirly - Notre exclusivité",
    "price": "1699",
    "image": "https://www.toysrus.ca/dw/image/v2/BDFX_PRD/on/demandware.static/-/Sites-toys-master-catalog/default/dw465be6bd/images/B43B6AED_1.jpg",
    "description": "Little Lot - Rampe de voiture Swirly Whirly - Notre exclusivité",
    "url": "https://www.toysrus.ca/fr/Little-Lot---Rampe-de-voiture-Swirly-Whirly---Notre-exclusivite/B43B6AED.html",
    "categories": [
        "vdjSQqKnTw6VVik-7a3i3g",
        "k1dYuCMyRxenOpsOzZXidg",
        "KZZsR5bdRIC5lTNJeyihTw",
        "MdvawtJvSomMvUa1KjQc_A",
        "JptOk_sgRPO6qa9Ojjq5pA",
        "ufviqKmGQNq5gej63royHg",
        "V6F5qJDST4-SDE3PvCAjqg",
        "nLE2pK09RWWGiTrGV-IhRw",
        "YoWnZV46QhOKwjAMbt3Ibw"
    ]
}