{
    "id": "B4D91868",
    "name": "Ty Squish Zoey Pink And Black Striped Zebra 10 inch",
    "price": "999",
    "image": "https://www.toysrus.ca/dw/image/v2/BDFX_PRD/on/demandware.static/-/Sites-toys-master-catalog/default/dw256ad3ee/images/B4D91868_1.jpg",
    "description": "Ty Squish Zoey Pink And Black Striped Zebra 10 inch",
    "url": "https://www.toysrus.ca/fr/Ty-Squish-Zoey-Pink-And-Black-Striped-Zebra-10-inch/B4D91868.html",
    "categories": [
        "rFlTVotoSuuUXYkfGrXA2A",
        "vdjSQqKnTw6VVik-7a3i3g",
        "MdvawtJvSomMvUa1KjQc_A",
        "YoWnZV46QhOKwjAMbt3Ibw"
    ]
}