{
    "id": "C47C1A92",
    "name": "Jeu de marqueurs Glow Fusion - Créatures marines",
    "price": "1799",
    "image": "https://www.toysrus.ca/dw/image/v2/BDFX_PRD/on/demandware.static/-/Sites-toys-master-catalog/default/dwbc239a38/images/C47C1A92_1.jpg",
    "description": "Jeu de marqueurs Glow Fusion - Créatures marines",
    "url": "https://www.toysrus.ca/fr/Jeu-de-marqueurs-Glow-Fusion---Creatures-marines/C47C1A92.html",
    "categories": [
        "1fjjZGjyQQ289DQZw1JMdw",
        "oum-7vxuTbeC_7cuZaEQBA",
        "MdvawtJvSomMvUa1KjQc_A",
        "wB8JkNLKTD6LAnQHDVh_Kw",
        "S-dx9fVvQeaj9Om-UzWcIQ",
        "YoWnZV46QhOKwjAMbt3Ibw"
    ]
}