{
    "id": "C49D3A78",
    "name": "Squishmallows 12\" - Bevin la Barbe à Papa Rose et Bleue",
    "price": 2699,
    "image": "https://www.toysrus.ca/dw/image/v2/BDFX_PRD/on/demandware.static/-/Sites-toys-master-catalog/default/dw07cbd4bf/images/C49D3A78_1.jpg",
    "description": "Squishmallows 12\" - Bevin la Barbe à Papa Rose et Bleue",
    "url": "https://www.toysrus.ca/fr/Squishmallows-12----Bevin-la-Barbe-a-Papa-Rose-et-Bleue/C49D3A78.html",
    "categories": [
        "rFlTVotoSuuUXYkfGrXA2A",
        "vdjSQqKnTw6VVik-7a3i3g",
        "KZZsR5bdRIC5lTNJeyihTw",
        "MdvawtJvSomMvUa1KjQc_A",
        "YoWnZV46QhOKwjAMbt3Ibw"
    ]
}