{
    "id": "D4144888",
    "name": "Animal en Peluche Blue's Clues et You! Blowing Kisses Blue avec Sons et Mouvement, Chien",
    "price": "4499",
    "image": "https://www.toysrus.ca/dw/image/v2/BDFX_PRD/on/demandware.static/-/Sites-toys-master-catalog/default/dwda4fc266/images/D4144888_1.jpg",
    "description": "Animal en Peluche Blue's Clues et You! Blowing Kisses Blue avec Sons et Mouvement, Chien",
    "url": "https://www.toysrus.ca/fr/Animal-en-Peluche-Blue-s-Clues-et-You--Blowing-Kisses-Blue-avec-Sons-et-Mouvement--Chien/D4144888.html",
    "categories": [
        "vdjSQqKnTw6VVik-7a3i3g",
        "MdvawtJvSomMvUa1KjQc_A",
        "nLE2pK09RWWGiTrGV-IhRw",
        "YoWnZV46QhOKwjAMbt3Ibw"
    ]
}