{
    "id": "D48978D4",
    "name": "LEGO Speed Champions Mercedes-AMG F1 W12 E Performance et Mercedes-AMG Project One",
    "price": "4999",
    "image": "https://www.toysrus.ca/dw/image/v2/BDFX_PRD/on/demandware.static/-/Sites-toys-master-catalog/default/dw6aae5652/images/D48978D4_1.jpg",
    "description": "LEGO Speed Champions Mercedes-AMG F1 W12 E Performance et Mercedes-AMG Project One",
    "url": "https://www.toysrus.ca/fr/LEGO%C2%A0Speed%C2%A0Champions%C2%A0Mercedes-AMG-F1-W12-E-Performance-et-Mercedes-AMG-Project-One/D48978D4.html",
    "categories": [
        "1fjjZGjyQQ289DQZw1JMdw",
        "MdvawtJvSomMvUa1KjQc_A",
        "JptOk_sgRPO6qa9Ojjq5pA",
        "V6F5qJDST4-SDE3PvCAjqg",
        "yMgFZPBSSbS0W0_67S6H2A",
        "YoWnZV46QhOKwjAMbt3Ibw"
    ]
}