{
    "id": "E47F5902",
    "name": "Melissa and Doug - Fun At The Fair- Terrain d'aventure Minigolf",
    "price": 3999,
    "image": "https://www.toysrus.ca/dw/image/v2/BDFX_PRD/on/demandware.static/-/Sites-toys-master-catalog/default/dw9f49ea14/images/E47F5902_1.jpg",
    "description": "Melissa and Doug - Fun At The Fair- Terrain d'aventure Minigolf",
    "url": "https://www.toysrus.ca/fr/Melissa-and-Doug---Fun-At-The-Fair--Terrain-d-aventure-Minigolf/E47F5902.html",
    "categories": [
        "vdjSQqKnTw6VVik-7a3i3g",
        "MdvawtJvSomMvUa1KjQc_A",
        "nLE2pK09RWWGiTrGV-IhRw",
        "YoWnZV46QhOKwjAMbt3Ibw"
    ]
}