{
    "id": "E489E9F1",
    "name": "PAW Patrol, Chase Hero Paws, Jouet en peluche du film pour jeu de rôle avec 10 sons et expressions",
    "price": "1648",
    "image": "https://www.toysrus.ca/dw/image/v2/BDFX_PRD/on/demandware.static/-/Sites-toys-master-catalog/default/dw8b5a0dde/images/E489E9F1_1.jpg",
    "description": "PAW Patrol, Chase Hero Paws, Jouet en peluche du film pour jeu de rôle avec 10 sons et expressions",
    "url": "https://www.toysrus.ca/fr/PAW-Patrol--Chase-Hero-Paws--Jouet-en-peluche-du-film-pour-jeu-de-role-avec-10-sons-et-expressions/E489E9F1.html",
    "categories": [
        "vdjSQqKnTw6VVik-7a3i3g",
        "MdvawtJvSomMvUa1KjQc_A",
        "nLE2pK09RWWGiTrGV-IhRw",
        "YoWnZV46QhOKwjAMbt3Ibw"
    ]
}