{
    "id": "E4951B30",
    "name": "Playmobil - Plowhorn et D'Angelo",
    "price": 8299,
    "image": "https://www.toysrus.ca/dw/image/v2/BDFX_PRD/on/demandware.static/-/Sites-toys-master-catalog/default/dw4562ee91/images/E4951B30_1.jpg",
    "description": "Playmobil - Plowhorn et D'Angelo",
    "url": "https://www.toysrus.ca/fr/Playmobil---Plowhorn-et-D-Angelo/E4951B30.html",
    "categories": [
        "KZZsR5bdRIC5lTNJeyihTw",
        "MdvawtJvSomMvUa1KjQc_A",
        "yMgFZPBSSbS0W0_67S6H2A",
        "YoWnZV46QhOKwjAMbt3Ibw"
    ]
}