{
    "id": "E4F2A9B0",
    "name": "Poupée-Mannequin Artistique Rainbow High Color and Create Avec Yeux Violets",
    "price": "4999",
    "image": "https://www.toysrus.ca/dw/image/v2/BDFX_PRD/on/demandware.static/-/Sites-toys-master-catalog/default/dwb80e715a/images/E4F2A9B0_1.jpg",
    "description": "Poupée-Mannequin Artistique Rainbow High Color and Create Avec Yeux Violets",
    "url": "https://www.toysrus.ca/fr/Poupee-Mannequin-Artistique-Rainbow-High-Color-and-Create-Avec-Yeux-Violets/E4F2A9B0.html",
    "categories": [
        "vdjSQqKnTw6VVik-7a3i3g",
        "KZZsR5bdRIC5lTNJeyihTw",
        "MdvawtJvSomMvUa1KjQc_A",
        "kSzVH6Q3RdGcG-yk9-k2jg",
        "omLQner7Ssm_qB_TXJDkGA",
        "-CF92pItTH2OCr5NML3LLw",
        "YoWnZV46QhOKwjAMbt3Ibw"
    ]
}