{
    "id": "EC179138",
    "name": "Passeur de hockey miniature de la NHL, de Franklin Sports",
    "price": "4999",
    "image": "https://www.toysrus.ca/dw/image/v2/BDFX_PRD/on/demandware.static/-/Sites-toys-master-catalog/default/dw8f4fb2a3/images/EC179138_1.jpg",
    "description": "Passeur de hockey miniature de la NHL, de Franklin Sports",
    "url": "https://www.toysrus.ca/fr/Passeur-de-hockey-miniature-de-la-NHL--de-Franklin-Sports/EC179138.html",
    "categories": [
        "vdjSQqKnTw6VVik-7a3i3g",
        "MdvawtJvSomMvUa1KjQc_A",
        "EcEq2U1VRiaWkujI4AO-hg",
        "zvDQSNjGT5GMtkCUN9y4hg",
        "nR3vqPRmSISP5EWA8s8nXw",
        "YoWnZV46QhOKwjAMbt3Ibw"
    ]
}