{
    "id": "F475A904",
    "name": "Fisher Price-Disney 100-Coffret Mickey et ses amis-Coffret",
    "price": "3499",
    "image": "https://www.toysrus.ca/dw/image/v2/BDFX_PRD/on/demandware.static/-/Sites-toys-master-catalog/default/dw8cb5ea58/images/F475A904_1.jpg",
    "description": "Fisher Price-Disney 100-Coffret Mickey et ses amis-Coffret",
    "url": "https://www.toysrus.ca/fr/Fisher-Price-Disney-100-Coffret-Mickey-et-ses-amis-Coffret/F475A904.html",
    "categories": [
        "vdjSQqKnTw6VVik-7a3i3g",
        "k1dYuCMyRxenOpsOzZXidg",
        "MdvawtJvSomMvUa1KjQc_A",
        "nLE2pK09RWWGiTrGV-IhRw",
        "YoWnZV46QhOKwjAMbt3Ibw"
    ]
}