{
    "id": "F48FBA10",
    "name": "POP: My Hero Academia-Shoto Todoroki - Notre exclusivité",
    "price": 1999,
    "image": "https://www.toysrus.ca/dw/image/v2/BDFX_PRD/on/demandware.static/-/Sites-toys-master-catalog/default/dwe367299b/images/F48FBA10_1.jpg",
    "description": "POP: My Hero Academia-Shoto Todoroki - Notre exclusivité",
    "url": "https://www.toysrus.ca/fr/POP--My-Hero-Academia-Shoto-Todoroki---Notre-exclusivite/F48FBA10.html",
    "categories": [
        "1fjjZGjyQQ289DQZw1JMdw",
        "hFPgaxjyTS-09FMgOvQS9g",
        "KZZsR5bdRIC5lTNJeyihTw",
        "MdvawtJvSomMvUa1KjQc_A",
        "SoeT2PFORRuHrUwzGVMbug",
        "YoWnZV46QhOKwjAMbt3Ibw"
    ]
}