{
    "id": "2117447F",
    "name": "Rollplay 6V BMW M8 GTE",
    "price": 39999,
    "image": "https://www.toysrus.ca/dw/image/v2/BDFX_PRD/on/demandware.static/-/Sites-toys-master-catalog/default/dwc251ba5d/images/2117447F_1.jpg",
    "description": "Rollplay 6V BMW M8 GTE",
    "url": "https://www.toysrus.ca/fr/Rollplay-6V-BMW-M8-GTE/2117447F.html",
    "categories": [
        "vdjSQqKnTw6VVik-7a3i3g",
        "MdvawtJvSomMvUa1KjQc_A",
        "mQkNSvHcShiKaCDqjehk3A",
        "hVSzt2gbTWutwbGYjM_4ww",
        "nR3vqPRmSISP5EWA8s8nXw",
        "YoWnZV46QhOKwjAMbt3Ibw"
    ]
}