{
    "id": "2682EDC7",
    "name": "Ensemble de compagnon d'épicerie Fresh Mart de Melissa & Doug",
    "price": 4999,
    "image": "https://www.toysrus.ca/dw/image/v2/BDFX_PRD/on/demandware.static/-/Sites-toys-master-catalog/default/dw2fc791ee/images/2682EDC7_1.jpg",
    "description": "Ensemble de compagnon d'épicerie Fresh Mart de Melissa & Doug",
    "url": "https://www.toysrus.ca/fr/Ensemble-de-compagnon-d-epicerie-Fresh-Mart-de-Melissa-and-Doug/2682EDC7.html",
    "categories": [
        "vdjSQqKnTw6VVik-7a3i3g",
        "MdvawtJvSomMvUa1KjQc_A",
        "p4GuDYzBTseOWhFMOiTgpw",
        "H_wmbx3lSDmpJYqSeU4WRA",
        "Ek5AfUwASGWAcmFz9SzzoQ",
        "YoWnZV46QhOKwjAMbt3Ibw"
    ]
}