{
    "id": "34E62812",
    "name": "Tête De Crapaud Junior",
    "price": 2299,
    "image": "https://www.toysrus.ca/dw/image/v2/BDFX_PRD/on/demandware.static/-/Sites-toys-master-catalog/default/dw72c4ac1b/images/34E62812_1.jpg",
    "description": "Tête De Crapaud Junior",
    "url": "https://www.toysrus.ca/fr/Tete-De-Crapaud-Junior/34E62812.html",
    "categories": [
        "hFPgaxjyTS-09FMgOvQS9g",
        "vdjSQqKnTw6VVik-7a3i3g",
        "KZZsR5bdRIC5lTNJeyihTw",
        "MdvawtJvSomMvUa1KjQc_A",
        "SoeT2PFORRuHrUwzGVMbug",
        "YoWnZV46QhOKwjAMbt3Ibw"
    ]
}