{
    "id": "44AD79CF",
    "name": "VTech Switch et Go - EggiRex, le T-Rex - Édition française",
    "price": 1499,
    "image": "https://www.toysrus.ca/dw/image/v2/BDFX_PRD/on/demandware.static/-/Sites-toys-master-catalog/default/dwde700b69/images/44AD79CF_1.jpg",
    "description": "VTech Switch et Go - EggiRex, le T-Rex - Édition française",
    "url": "https://www.toysrus.ca/fr/VTech-Switch-et-Go---EggiRex--le-T-Rex---Edition-francaise/44AD79CF.html",
    "categories": [
        "vdjSQqKnTw6VVik-7a3i3g",
        "MdvawtJvSomMvUa1KjQc_A",
        "JptOk_sgRPO6qa9Ojjq5pA",
        "V6F5qJDST4-SDE3PvCAjqg",
        "nLE2pK09RWWGiTrGV-IhRw",
        "YoWnZV46QhOKwjAMbt3Ibw"
    ]
}