{
    "id": "8414DB8F",
    "name": "Disney Mickey And Friends \"Food Fight\" - Édition anglaise",
    "price": 2699,
    "image": "https://www.toysrus.ca/dw/image/v2/BDFX_PRD/on/demandware.static/-/Sites-toys-master-catalog/default/dw17ea46cd/images/8414DB8F_1.jpg",
    "description": "Disney Mickey And Friends \"Food Fight\" - Édition anglaise",
    "url": "https://www.toysrus.ca/fr/Disney-Mickey-And-Friends--Food-Fight----Edition-anglaise/8414DB8F.html",
    "categories": [
        "KZZsR5bdRIC5lTNJeyihTw",
        "MdvawtJvSomMvUa1KjQc_A",
        "H_wmbx3lSDmpJYqSeU4WRA",
        "YoWnZV46QhOKwjAMbt3Ibw"
    ]
}