{
    "id": "84EA4A34",
    "name": "Jurassic World-Tyrannosaurus Rex-Jouet dinosaure avec sons",
    "price": 6499,
    "image": "https://www.toysrus.ca/dw/image/v2/BDFX_PRD/on/demandware.static/-/Sites-toys-master-catalog/default/dwb7bf3dc4/images/84EA4A34_1.jpg",
    "description": "Jurassic World-Tyrannosaurus Rex-Jouet dinosaure avec sons",
    "url": "https://www.toysrus.ca/fr/Jurassic-World-Tyrannosaurus-Rex-Jouet-dinosaure-avec-sons/84EA4A34.html",
    "categories": [
        "2LAIi61IROKwIcGCtn1n1g",
        "LRsfCDC0TyG2dyvcxjN-ig",
        "vdjSQqKnTw6VVik-7a3i3g",
        "KZZsR5bdRIC5lTNJeyihTw",
        "MdvawtJvSomMvUa1KjQc_A",
        "YoWnZV46QhOKwjAMbt3Ibw"
    ]
}