{
    "id": "F3E52689",
    "name": "LeapFrog LeapStart Preschool (Level 1) Scout & Friends Math with Problem Solving Activity Book- Édition anglaise",
    "price": 999,
    "image": "https://www.toysrus.ca/dw/image/v2/BDFX_PRD/on/demandware.static/-/Sites-toys-master-catalog/default/dwb50699db/images/F3E52689_1.jpg",
    "description": "LeapFrog LeapStart Preschool (Level 1) Scout & Friends Math with Problem Solving Activity Book- Édition anglaise",
    "url": "https://www.toysrus.ca/fr/LeapFrog-LeapStart-Preschool--Level-1--Scout-and-Friends-Math-with-Problem-Solving-Activity-Book--Edition-anglaise/F3E52689.html",
    "categories": [
        "k1dYuCMyRxenOpsOzZXidg",
        "MdvawtJvSomMvUa1KjQc_A",
        "yxmm504pSfqjUZkwHqug1Q",
        "H-0oXd77RpuqhVvQ4Ncdlw",
        "Xgn7P7_hTGGElQZn0i_c5A",
        "SqNRVU9HTHuhIqHxOJaN8w",
        "YoWnZV46QhOKwjAMbt3Ibw"
    ]
}